azure/mgmt/frontdoor/__init__.py
azure/mgmt/frontdoor/_configuration.py
azure/mgmt/frontdoor/_front_door_management_client.py
azure/mgmt/frontdoor/_patch.py
azure/mgmt/frontdoor/_serialization.py
azure/mgmt/frontdoor/_vendor.py
azure/mgmt/frontdoor/_version.py
azure/mgmt/frontdoor/py.typed
azure/mgmt/frontdoor/aio/__init__.py
azure/mgmt/frontdoor/aio/_configuration.py
azure/mgmt/frontdoor/aio/_front_door_management_client.py
azure/mgmt/frontdoor/aio/_patch.py
azure/mgmt/frontdoor/aio/operations/__init__.py
azure/mgmt/frontdoor/aio/operations/_endpoints_operations.py
azure/mgmt/frontdoor/aio/operations/_experiments_operations.py
azure/mgmt/frontdoor/aio/operations/_front_door_name_availability_operations.py
azure/mgmt/frontdoor/aio/operations/_front_door_name_availability_with_subscription_operations.py
azure/mgmt/frontdoor/aio/operations/_front_doors_operations.py
azure/mgmt/frontdoor/aio/operations/_frontend_endpoints_operations.py
azure/mgmt/frontdoor/aio/operations/_managed_rule_sets_operations.py
azure/mgmt/frontdoor/aio/operations/_network_experiment_profiles_operations.py
azure/mgmt/frontdoor/aio/operations/_patch.py
azure/mgmt/frontdoor/aio/operations/_policies_operations.py
azure/mgmt/frontdoor/aio/operations/_preconfigured_endpoints_operations.py
azure/mgmt/frontdoor/aio/operations/_reports_operations.py
azure/mgmt/frontdoor/aio/operations/_rules_engines_operations.py
azure/mgmt/frontdoor/models/__init__.py
azure/mgmt/frontdoor/models/_front_door_management_client_enums.py
azure/mgmt/frontdoor/models/_models_py3.py
azure/mgmt/frontdoor/models/_patch.py
azure/mgmt/frontdoor/operations/__init__.py
azure/mgmt/frontdoor/operations/_endpoints_operations.py
azure/mgmt/frontdoor/operations/_experiments_operations.py
azure/mgmt/frontdoor/operations/_front_door_name_availability_operations.py
azure/mgmt/frontdoor/operations/_front_door_name_availability_with_subscription_operations.py
azure/mgmt/frontdoor/operations/_front_doors_operations.py
azure_mgmt_frontdoor-1.2.0.dist-info/LICENSE
azure_mgmt_frontdoor-1.2.0.dist-info/METADATA
azure_mgmt_frontdoor-1.2.0.dist-info/WHEEL
azure_mgmt_frontdoor-1.2.0.dist-info/top_level.txt
azure_mgmt_frontdoor-1.2.0.dist-info/RECORD
